nvidia_services/__init__.py
nvidia_services/embeddings/__init__.py
nvidia_services/embeddings/base.py
nvidia_services/embeddings/nvidia_embeddings.py
nvidia_services/endpoints/__init__.py
nvidia_services/endpoints/nvidia_endpoints.py
nvidia_services/models/__init__.py
nvidia_services/models/base.py
nvidia_services/models/mistralai_models.py
nvidia_services/retrievals/__init__.py
nvidia_services/retrievals/base.py
nvidia_services/retrievals/nvidia_reranker.py
nvidia_services-0.0.2.dist-info/METADATA
nvidia_services-0.0.2.dist-info/WHEEL
nvidia_services-0.0.2.dist-info/top_level.txt
nvidia_services-0.0.2.dist-info/RECORD
